<?xml version="1.0" encoding="utf-8"?>
<cce>
  <item type="CCE" id="CCE-3416-5">
    <description>The rhnsd service should be enabled or disabled as appropriate.</description>
    <parameters>
      <parameter>enabled</parameter>
      <parameter>disabled</parameter>
    </parameters>
    <technicalmechanisms>via chkconfig</technicalmechanisms>
    <refs>
      <ref source="NSA Guide to the Secure Configuration of Red Hat Enterprise Linux 5 (Section 2.1.2.2)">disabled</ref>      
    </refs>
  </item>
  <item type="CCE" id="CCE-4218-4">
    <description>The rhnsd service should be enabled or disabled as appropriate.</description>
    <parameters>
      <parameter>enabled</parameter>
      <parameter>disabled</parameter>
    </parameters>
    <technicalmechanisms>via chkconfig</technicalmechanisms>
    <refs>
      <ref source="NSA Guide to the Secure Configuration of Red Hat Enterprise Linux 5 (Section 2.1.2.2)">disabled</ref>      
    </refs>
  </item>
  </cce>
  
